[
  {
    "Id": 79,
    "Name": "Program_1",
    "Description": "This is program 1",
    "IsActive": false,
    "ActualFlow": 0.0,
    "ActualWaterQuantity": 3600.0,
    "ExpectedEndOfIrrigation": "",
    "ExpectedFlow": 0.0,
    "IndexInGroup": 1,
    "IrrigationBasis": "Time",
    "IsSuspend": false,
    "GroupStatus": "Finished",
    "IntervalBetweenCycles": 0,
    "IntervalBetweenCyclesType": "StartToStart",
    "IrrigationDow": 0,
    "IrrigationDaysInterval": 1,
    "IrrigationDaysType": "DaysInterval",
    "GroupName": "",
    "NumberOfCycles": 1,
    "RemainingCycles": 0,
    "RemainingDays": 1,
    "StartTime": 25200,
    "GroupStopTime": 0,
    "LastFinishTime": "",
    "LastStartTime": "",
    "MinimumWaterQuantity": 0.0,
    "MaximumWaterQuantity": 0.0,
    "PostFertQuantity": 0.0,
    "ProgramStopTime": 0,
    "ProgramStatus": "Ready",
    "ProgramRemainingCycles": 0,
    "RemainingWater": 3600.0,
    "UserFactor": 100.0,
    "WaterDebt": 0.0,
    "WaterQuantity": 3600.0,
    "HasCommFailureWithFieldUnit": true,
    "HasCommFailureWithMeter": false,
    "LastSample": "20180218123616"
  },
  {
    "Id": 80,
    "Name": "Program_2",
    "Description": "This is program 2",
    "IsActive": false,
    "ActualFlow": 4.5,
    "ActualWaterQuantity": 3700.0,
    "ExpectedEndOfIrrigation": "",
    "ExpectedFlow": 0.0,
    "IndexInGroup": 1,
    "IrrigationBasis": "Time",
    "IsSuspend": false,
    "GroupStatus": "Finished",
    "IntervalBetweenCycles": 0,
    "IntervalBetweenCyclesType": "StartToStart",
    "IrrigationDow": 0,
    "IrrigationDaysInterval": 1,
    "IrrigationDaysType": "DaysInterval",
    "GroupName": "",
    "NumberOfCycles": 1,
    "RemainingCycles": 0,
    "RemainingDays": 1,
    "StartTime": 25200,
    "GroupStopTime": 0,
    "LastFinishTime": "",
    "LastStartTime": "",
    "MinimumWaterQuantity": 0.0,
    "MaximumWaterQuantity": 0.0,
    "PostFertQuantity": 0.0,
    "ProgramStopTime": 0,
    "ProgramStatus": "Ready",
    "ProgramRemainingCycles": 0,
    "RemainingWater": 3700.0,
    "UserFactor": 100.0,
    "WaterDebt": 0.0,
    "WaterQuantity": 3700.0,
    "HasCommFailureWithFieldUnit": true,
    "HasCommFailureWithMeter": false,
    "LastSample": "20180218124616"
  },
  {
    "Id": 81,
    "Name": "Program_3",
    "Description": "This is program 3",
    "IsActive": false,
    "ActualFlow": 7.0,
    "ActualWaterQuantity": 3200.0,
    "ExpectedEndOfIrrigation": "",
    "ExpectedFlow": 0.0,
    "IndexInGroup": 1,
    "IrrigationBasis": "Time",
    "IsSuspend": false,
    "GroupStatus": "Finished",
    "IntervalBetweenCycles": 0,
    "IntervalBetweenCyclesType": "StartToStart",
    "IrrigationDow": 0,
    "IrrigationDaysInterval": 1,
    "IrrigationDaysType": "DaysInterval",
    "GroupName": "",
    "NumberOfCycles": 1,
    "RemainingCycles": 0,
    "RemainingDays": 1,
    "StartTime": 25200,
    "GroupStopTime": 0,
    "LastFinishTime": "",
    "LastStartTime": "",
    "MinimumWaterQuantity": 0.0,
    "MaximumWaterQuantity": 0.0,
    "PostFertQuantity": 0.0,
    "ProgramStopTime": 0,
    "ProgramStatus": "Ready",
    "ProgramRemainingCycles": 0,
    "RemainingWater": 3200.0,
    "UserFactor": 100.0,
    "WaterDebt": 0.0,
    "WaterQuantity": 3200.0,
    "HasCommFailureWithFieldUnit": true,
    "HasCommFailureWithMeter": false,
    "LastSample": "20180218152616"
  }
]
